{
  "generatedAt": "2026-06-08T23:39:49.327Z",
  "note": "Automatically generated. Items keep titles, summaries, source names and original links only.",
  "counts": {
    "total": 246,
    "safety": 81,
    "mining": 81,
    "underground": 84,
    "job": 237,
    "social": 9
  },
  "errors": [
    {
      "source": "应届生求职网",
      "major": "safety",
      "query": "安全工程 实习",
      "message": "HTTP 404"
    },
    {
      "source": "应届生求职网",
      "major": "safety",
      "query": "EHS 实习",
      "message": "HTTP 404"
    },
    {
      "source": "应届生求职网",
      "major": "safety",
      "query": "HSE 实习",
      "message": "HTTP 404"
    },
    {
      "source": "应届生求职网",
      "major": "safety",
      "query": "安全评价 实习",
      "message": "HTTP 404"
    },
    {
      "source": "应届生求职网",
      "major": "safety",
      "query": "安全工程 面经",
      "message": "HTTP 404"
    },
    {
      "source": "应届生求职网",
      "major": "mining",
      "query": "采矿工程 实习",
      "message": "HTTP 404"
    },
    {
      "source": "应届生求职网",
      "major": "mining",
      "query": "矿山 实习",
      "message": "HTTP 404"
    },
    {
      "source": "应届生求职网",
      "major": "mining",
      "query": "智能矿山 实习",
      "message": "HTTP 404"
    },
    {
      "source": "应届生求职网",
      "major": "mining",
      "query": "采矿工程 面经",
      "message": "HTTP 404"
    },
    {
      "source": "应届生求职网",
      "major": "mining",
      "query": "矿业 校招",
      "message": "HTTP 404"
    },
    {
      "source": "应届生求职网",
      "major": "underground",
      "query": "城市地下空间工程 实习",
      "message": "HTTP 404"
    },
    {
      "source": "应届生求职网",
      "major": "underground",
      "query": "盾构 实习",
      "message": "HTTP 404"
    },
    {
      "source": "应届生求职网",
      "major": "underground",
      "query": "隧道 实习",
      "message": "HTTP 404"
    },
    {
      "source": "应届生求职网",
      "major": "underground",
      "query": "地铁工程 实习",
      "message": "HTTP 404"
    },
    {
      "source": "应届生求职网",
      "major": "underground",
      "query": "基坑监测 实习",
      "message": "HTTP 404"
    }
  ],
  "items": [
    {
      "id": "b1bf9f34a1991fb7",
      "major": "safety",
      "category": "job",
      "platform": "精选方向",
      "source": "精选方向",
      "title": "EHS / HSE 实习：制造、新能源、化工、施工企业优先关注",
      "summary": "适合安全工程学生积累体系管理、隐患排查、培训、事故案例复盘和现场沟通经验。",
      "url": "https://www.shixiseng.com/interns?keyword=EHS%E5%AE%9E%E4%B9%A0",
      "status": "seed"
    },
    {
      "id": "3ef93b75bb695a24",
      "major": "safety",
      "category": "social",
      "platform": "精选方向",
      "source": "精选方向",
      "title": "安全工程实习面经：重点检索 EHS、HSE、安全评价和应急管理",
      "summary": "社媒经验适合了解真实投递路径、岗位日常和面试问题，请回到原平台核验信息。",
      "url": "https://search.bilibili.com/all?keyword=%E5%AE%89%E5%85%A8%E5%B7%A5%E7%A8%8B%20%E5%AE%9E%E4%B9%A0%20%E9%9D%A2%E7%BB%8F",
      "status": "seed"
    },
    {
      "id": "26d5e408b473ad18",
      "major": "mining",
      "category": "job",
      "platform": "精选方向",
      "source": "精选方向",
      "title": "智能矿山 / 矿业数字化实习：关注建模、调度与安全监测",
      "summary": "适合采矿工程学生展示 CAD、三维建模、通风安全、生产调度和现场理解能力。",
      "url": "https://www.shixiseng.com/interns?keyword=%E6%99%BA%E8%83%BD%E7%9F%BF%E5%B1%B1",
      "status": "seed"
    },
    {
      "id": "9ee7039f4222c0b3",
      "major": "mining",
      "category": "social",
      "platform": "精选方向",
      "source": "精选方向",
      "title": "采矿工程实习经验：重点检索矿山现场、智能矿山、央国企实习",
      "summary": "适合了解矿山岗位真实工作环境、暑期实习安排和专业能力要求。",
      "url": "https://search.bilibili.com/all?keyword=%E9%87%87%E7%9F%BF%E5%B7%A5%E7%A8%8B%20%E5%AE%9E%E4%B9%A0",
      "status": "seed"
    },
    {
      "id": "298714dd84a27a85",
      "major": "underground",
      "category": "job",
      "platform": "精选方向",
      "source": "精选方向",
      "title": "盾构 / 隧道 / 地铁工程实习：关注施工、监测和资料管理",
      "summary": "适合城市地下空间工程学生积累项目现场、BIM 协同、监测数据和工程文档经验。",
      "url": "https://www.shixiseng.com/interns?keyword=%E7%9B%BE%E6%9E%84%E5%AE%9E%E4%B9%A0",
      "status": "seed"
    },
    {
      "id": "8d0cf3deba1edb1c",
      "major": "underground",
      "category": "social",
      "platform": "精选方向",
      "source": "精选方向",
      "title": "地下空间工程实习经验：重点检索盾构、地铁、基坑监测、隧道工程",
      "summary": "适合了解施工现场、项目资料、监测岗位和工程单位实习体验。",
      "url": "https://search.bilibili.com/all?keyword=%E5%9C%B0%E4%B8%8B%E7%A9%BA%E9%97%B4%E5%B7%A5%E7%A8%8B%20%E5%AE%9E%E4%B9%A0",
      "status": "seed"
    },
    {
      "id": "0785834adb053420",
      "major": "safety",
      "category": "job",
      "platform": "实习僧",
      "source": "实习僧",
      "title": "安全&#xe4e5&#xe4ec实习&#xf16c",
      "summary": "来自 实习僧 的安全工程相关实习/就业信息，请以原网站发布时间和要求为准。",
      "url": "https://www.shixiseng.com/intern/inn_ixhwpryaqgbc?pcm=pc_SearchList",
      "status": "auto"
    },
    {
      "id": "4dcca45813d801a2",
      "major": "safety",
      "category": "job",
      "platform": "实习僧",
      "source": "实习僧",
      "title": "安全实习&#xf16c",
      "summary": "来自 实习僧 的安全工程相关实习/就业信息，请以原网站发布时间和要求为准。",
      "url": "https://www.shixiseng.com/intern/inn_huvfistxvrhv?pcm=pc_SearchList",
      "status": "auto"
    },
    {
      "id": "f51918d4db6259a7",
      "major": "safety",
      "category": "job",
      "platform": "实习僧",
      "source": "实习僧",
      "title": "&#xe4e5&#xe4ec实习&#xf16c",
      "summary": "来自 实习僧 的安全工程相关实习/就业信息，请以原网站发布时间和要求为准。",
      "url": "https://www.shixiseng.com/intern/inn_okzwfs2kau2k?pcm=pc_SearchList",
      "status": "auto"
    },
    {
      "id": "7b584a9532dafba3",
      "major": "safety",
      "category": "job",
      "platform": "实习僧",
      "source": "实习僧",
      "title": "安全产品技术部-安全研发实习&#xf16c（&#xe6c4）",
      "summary": "来自 实习僧 的安全工程相关实习/就业信息，请以原网站发布时间和要求为准。",
      "url": "https://www.shixiseng.com/intern/inn_xbymajywy3y3?pcm=pc_SearchList",
      "status": "auto"
    },
    {
      "id": "d364f343e3a24c28",
      "major": "safety",
      "category": "job",
      "platform": "实习僧",
      "source": "实习僧",
      "title": "金融&#xe4e5&#xe4ec实习",
      "summary": "来自 实习僧 的安全工程相关实习/就业信息，请以原网站发布时间和要求为准。",
      "url": "https://www.shixiseng.com/intern/inn_uepub98lqcqh?pcm=pc_SearchList",
      "status": "auto"
    },
    {
      "id": "fe80a1e624718139",
      "major": "safety",
      "category": "job",
      "platform": "实习僧",
      "source": "实习僧",
      "title": "安全开发实习&#xf16c",
      "summary": "来自 实习僧 的安全工程相关实习/就业信息，请以原网站发布时间和要求为准。",
      "url": "https://www.shixiseng.com/intern/inn_rhgtzxjgxxgk?pcm=pc_SearchList",
      "status": "auto"
    },
    {
      "id": "2fe5e7b7db28efaf",
      "major": "safety",
      "category": "job",
      "platform": "实习僧",
      "source": "实习僧",
      "title": "实习&#xf16c-食品安全",
      "summary": "来自 实习僧 的安全工程相关实习/就业信息，请以原网站发布时间和要求为准。",
      "url": "https://www.shixiseng.com/intern/inn_1jcnltsmsnid?pcm=pc_SearchList",
      "status": "auto"
    },
    {
      "id": "0b550c7d7bf17018",
      "major": "safety",
      "category": "job",
      "platform": "智联招聘",
      "source": "智联招聘",
      "title": "安全工程实习生",
      "summary": "来自 智联招聘 的安全工程相关实习/就业信息，请以原网站发布时间和要求为准。",
      "url": "http://www.zhaopin.com/jobdetail/CC460859320J40749520711.htm",
      "status": "auto"
    },
    {
      "id": "d1f6afd882f6ee6f",
      "major": "safety",
      "category": "job",
      "platform": "智联招聘",
      "source": "智联招聘",
      "title": "安全工程技术服务实习生",
      "summary": "来自 智联招聘 的安全工程相关实习/就业信息，请以原网站发布时间和要求为准。",
      "url": "http://www.zhaopin.com/jobdetail/CC391428920J41013630804.htm",
      "status": "auto"
    },
    {
      "id": "282eab7a4cc81c9a",
      "major": "safety",
      "category": "job",
      "platform": "智联招聘",
      "source": "智联招聘",
      "title": "人力资源实习生（招聘助理/安全工程专业优先）",
      "summary": "来自 智联招聘 的安全工程相关实习/就业信息，请以原网站发布时间和要求为准。",
      "url": "http://www.zhaopin.com/jobdetail/CC138960290J40821848016.htm",
      "status": "auto"
    },
    {
      "id": "a91025d94495ec0a",
      "major": "safety",
      "category": "job",
      "platform": "智联招聘",
      "source": "智联招聘",
      "title": "信创与网络安全事业部-服务中心-网络工程实习生",
      "summary": "来自 智联招聘 的安全工程相关实习/就业信息，请以原网站发布时间和要求为准。",
      "url": "http://www.zhaopin.com/jobdetail/CC297756910J40891125612.htm",
      "status": "auto"
    },
    {
      "id": "520ce141ca7651ba",
      "major": "safety",
      "category": "job",
      "platform": "智联招聘",
      "source": "智联招聘",
      "title": "实习生（财务、行政、安全、运营、工程等）",
      "summary": "来自 智联招聘 的安全工程相关实习/就业信息，请以原网站发布时间和要求为准。",
      "url": "http://www.zhaopin.com/jobdetail/CCL1294364070J40776959312.htm",
      "status": "auto"
    },
    {
      "id": "a6dd707254691ae7",
      "major": "safety",
      "category": "job",
      "platform": "智联招聘",
      "source": "智联招聘",
      "title": "注册安全工程监理工程师",
      "summary": "来自 智联招聘 的安全工程相关公开信息，已按关键词自动归类。",
      "url": "http://www.zhaopin.com/jobdetail/CC364451310J40888760403.htm",
      "status": "auto"
    },
    {
      "id": "820a5598adbbe4b8",
      "major": "safety",
      "category": "job",
      "platform": "前程无忧",
      "source": "前程无忧",
      "title": "前程无忧：安全工程相关结果页",
      "summary": "已抓取到 前程无忧 的公开搜索页，但页面结构限制了列表解析，请打开原页面查看最新结果。",
      "url": "https://we.51job.com/pc/search?keyword=%E5%AE%89%E5%85%A8%E5%B7%A5%E7%A8%8B%20%E5%AE%9E%E4%B9%A0",
      "status": "search-page"
    },
    {
      "id": "b1013dd6f162b1c7",
      "major": "safety",
      "category": "job",
      "platform": "应届生求职网",
      "source": "应届生求职网",
      "title": "应届生求职网：安全工程 实习",
      "summary": "该来源本次自动抓取受限，已保留公开搜索入口，方便用户进入原平台查看。",
      "url": "https://www.yingjiesheng.com/so.php?word=%E5%AE%89%E5%85%A8%E5%B7%A5%E7%A8%8B%20%E5%AE%9E%E4%B9%A0",
      "status": "fallback"
    },
    {
      "id": "fa02aaedaafaff74",
      "major": "safety",
      "category": "job",
      "platform": "猎聘",
      "source": "猎聘",
      "title": "混凝土业务员招聘",
      "summary": "来自 猎聘 的安全工程相关实习/就业信息，请以原网站发布时间和要求为准。",
      "url": "https://www.liepin.com/zphntywy6l6w/",
      "status": "auto"
    },
    {
      "id": "cbfc6efe6be4c086",
      "major": "safety",
      "category": "job",
      "platform": "猎聘",
      "source": "猎聘",
      "title": "冰吧企划经理招聘",
      "summary": "来自 猎聘 的安全工程相关实习/就业信息，请以原网站发布时间和要求为准。",
      "url": "https://www.liepin.com/zpbbqhjl4p4w/",
      "status": "auto"
    },
    {
      "id": "b8279a12ed2dda5c",
      "major": "safety",
      "category": "job",
      "platform": "猎聘",
      "source": "猎聘",
      "title": "插画设计导师招聘",
      "summary": "来自 猎聘 的安全工程相关实习/就业信息，请以原网站发布时间和要求为准。",
      "url": "https://www.liepin.com/zpchsjds2w3o/",
      "status": "auto"
    },
    {
      "id": "21e6d3a4eb6873a7",
      "major": "safety",
      "category": "job",
      "platform": "猎聘",
      "source": "猎聘",
      "title": "拎包设计主管招聘",
      "summary": "来自 猎聘 的安全工程相关实习/就业信息，请以原网站发布时间和要求为准。",
      "url": "https://www.liepin.com/zplbsjzg8a1u/",
      "status": "auto"
    },
    {
      "id": "b10b9c31460a20e7",
      "major": "safety",
      "category": "job",
      "platform": "猎聘",
      "source": "猎聘",
      "title": "资深数据风控招聘",
      "summary": "来自 猎聘 的安全工程相关实习/就业信息，请以原网站发布时间和要求为准。",
      "url": "https://www.liepin.com/zpzssjfk3j5t/",
      "status": "auto"
    },
    {
      "id": "e46fff79e342f397",
      "major": "safety",
      "category": "job",
      "platform": "猎聘",
      "source": "猎聘",
      "title": "足疗推拿技师招聘",
      "summary": "来自 猎聘 的安全工程相关实习/就业信息，请以原网站发布时间和要求为准。",
      "url": "https://www.liepin.com/zpzltnjs3a6s/",
      "status": "auto"
    },
    {
      "id": "f037e7b20fda82f0",
      "major": "safety",
      "category": "job",
      "platform": "猎聘",
      "source": "猎聘",
      "title": "高级销售推广招聘",
      "summary": "来自 猎聘 的安全工程相关实习/就业信息，请以原网站发布时间和要求为准。",
      "url": "https://www.liepin.com/zpgjxstg1t5y/",
      "status": "auto"
    },
    {
      "id": "615d7cefee5dee03",
      "major": "safety",
      "category": "job",
      "platform": "猎聘",
      "source": "猎聘",
      "title": "家具建材仓库管理招聘",
      "summary": "来自 猎聘 的安全工程相关实习/就业信息，请以原网站发布时间和要求为准。",
      "url": "https://www.liepin.com/zpjjjcckgl6f5a/",
      "status": "auto"
    },
    {
      "id": "7d2bec3d72c87e7f",
      "major": "safety",
      "category": "job",
      "platform": "猎聘",
      "source": "猎聘",
      "title": "水电气规划工程师招聘",
      "summary": "来自 猎聘 的安全工程相关实习/就业信息，请以原网站发布时间和要求为准。",
      "url": "https://www.liepin.com/zpsdqghgcs6x2g/",
      "status": "auto"
    },
    {
      "id": "cf9e7949a5f2e5bf",
      "major": "safety",
      "category": "job",
      "platform": "猎聘",
      "source": "猎聘",
      "title": "外贸理单主管招聘",
      "summary": "来自 猎聘 的安全工程相关实习/就业信息，请以原网站发布时间和要求为准。",
      "url": "https://www.liepin.com/zpwmldzgf4t7/",
      "status": "auto"
    },
    {
      "id": "a14840204b5f349a",
      "major": "safety",
      "category": "job",
      "platform": "猎聘",
      "source": "猎聘",
      "title": "欧洲GTM总监招聘",
      "summary": "来自 猎聘 的安全工程相关实习/就业信息，请以原网站发布时间和要求为准。",
      "url": "https://www.liepin.com/zpozgtmzj9m4t/",
      "status": "auto"
    },
    {
      "id": "ea44d59005555f4c",
      "major": "safety",
      "category": "job",
      "platform": "猎聘",
      "source": "猎聘",
      "title": "跟单客服专员CSR招聘",
      "summary": "来自 猎聘 的安全工程相关实习/就业信息，请以原网站发布时间和要求为准。",
      "url": "https://www.liepin.com/zpgdkfzycsr1v8p/",
      "status": "auto"
    },
    {
      "id": "07790669604ff6dd",
      "major": "safety",
      "category": "social",
      "platform": "Bilibili",
      "source": "Bilibili",
      "title": "Bilibili：安全工程相关结果页",
      "summary": "已抓取到 Bilibili 的公开搜索页，但页面结构限制了列表解析，请打开原页面查看最新结果。",
      "url": "https://search.bilibili.com/all?keyword=%E5%AE%89%E5%85%A8%E5%B7%A5%E7%A8%8B%20%E5%AE%9E%E4%B9%A0",
      "status": "search-page"
    },
    {
      "id": "164f3f9b98173e2b",
      "major": "safety",
      "category": "social",
      "platform": "小红书",
      "source": "小红书",
      "title": "小红书：安全工程相关结果页",
      "summary": "已抓取到 小红书 的公开搜索页，但页面结构限制了列表解析，请打开原页面查看最新结果。",
      "url": "https://www.xiaohongshu.com/search_result?keyword=%E5%AE%89%E5%85%A8%E5%B7%A5%E7%A8%8B%20%E5%AE%9E%E4%B9%A0",
      "status": "search-page"
    },
    {
      "id": "84c31a19308d83dc",
      "major": "safety",
      "category": "job",
      "platform": "实习僧",
      "source": "实习僧",
      "title": "&#xf0ab&#xf1fb&#xe078实习&#xf16c",
      "summary": "来自 实习僧 的安全工程相关实习/就业信息，请以原网站发布时间和要求为准。",
      "url": "https://www.shixiseng.com/intern/inn_thgcshpfmemw?pcm=pc_SearchList",
      "status": "auto"
    },
    {
      "id": "c88bd8fae25ca2d5",
      "major": "safety",
      "category": "job",
      "platform": "实习僧",
      "source": "实习僧",
      "title": "&#xf0ab&#xf1fb&#xe078实习&#xf16c(&#xf1cc&#xe53c&#xf280&#xf1e5&#xe6c4&#xf1e5&#xf01a)",
      "summary": "来自 实习僧 的安全工程相关实习/就业信息，请以原网站发布时间和要求为准。",
      "url": "https://www.shixiseng.com/intern/inn_lhj8vbwfit4y?pcm=pc_SearchList",
      "status": "auto"
    },
    {
      "id": "dfb6d4dc183a5ce7",
      "major": "safety",
      "category": "job",
      "platform": "实习僧",
      "source": "实习僧",
      "title": "&#xf0ab&#xf1fb&#xe078管理实习&#xf16c",
      "summary": "来自 实习僧 的安全工程相关实习/就业信息，请以原网站发布时间和要求为准。",
      "url": "https://www.shixiseng.com/intern/inn_6cguppyvt8x6?pcm=pc_SearchList",
      "status": "auto"
    },
    {
      "id": "82d750a6d80098ed",
      "major": "safety",
      "category": "job",
      "platform": "实习僧",
      "source": "实习僧",
      "title": "部门助理实习&#xf16c（&#xf0ab&#xf1fb&#xe078部门）—&#xed1d&#xea6f&#xe744",
      "summary": "来自 实习僧 的安全工程相关实习/就业信息，请以原网站发布时间和要求为准。",
      "url": "https://www.shixiseng.com/intern/inn_flirn7n2dxrn?pcm=pc_SearchList",
      "status": "auto"
    },
    {
      "id": "c2150f755629c424",
      "major": "safety",
      "category": "job",
      "platform": "智联招聘",
      "source": "智联招聘",
      "title": "EHS实习生",
      "summary": "来自 智联招聘 的安全工程相关实习/就业信息，请以原网站发布时间和要求为准。",
      "url": "http://www.zhaopin.com/jobdetail/CC696872320J40943175808.htm",
      "status": "auto"
    },
    {
      "id": "3c46b7015541cef7",
      "major": "safety",
      "category": "job",
      "platform": "智联招聘",
      "source": "智联招聘",
      "title": "EHS安全员实习",
      "summary": "来自 智联招聘 的安全工程相关实习/就业信息，请以原网站发布时间和要求为准。",
      "url": "http://www.zhaopin.com/jobdetail/CC855482070J40775084610.htm",
      "status": "auto"
    },
    {
      "id": "9ffccae9f65b6ceb",
      "major": "safety",
      "category": "job",
      "platform": "智联招聘",
      "source": "智联招聘",
      "title": "校园新媒体运营营销推广实习生",
      "summary": "来自 智联招聘 的安全工程相关实习/就业信息，请以原网站发布时间和要求为准。",
      "url": "http://www.zhaopin.com/jobdetail/CCL1469968910J40451278316.htm",
      "status": "auto"
    },
    {
      "id": "2aafc378ba86e08c",
      "major": "safety",
      "category": "job",
      "platform": "智联招聘",
      "source": "智联招聘",
      "title": "新媒体运营实习生",
      "summary": "来自 智联招聘 的安全工程相关实习/就业信息，请以原网站发布时间和要求为准。",
      "url": "http://www.zhaopin.com/jobdetail/CC827021140J40847480313.htm",
      "status": "auto"
    },
    {
      "id": "df9ae47f9678ba20",
      "major": "safety",
      "category": "job",
      "platform": "智联招聘",
      "source": "智联招聘",
      "title": "2026届道桥工程造价专员（实习生）",
      "summary": "来自 智联招聘 的安全工程相关实习/就业信息，请以原网站发布时间和要求为准。",
      "url": "http://www.zhaopin.com/jobdetail/CC300775080J40845946807.htm",
      "status": "auto"
    },
    {
      "id": "3d67b0a8c8c78d12",
      "major": "safety",
      "category": "job",
      "platform": "智联招聘",
      "source": "智联招聘",
      "title": "三峡游游轮乘务员包吃住（接受实习生）",
      "summary": "来自 智联招聘 的安全工程相关实习/就业信息，请以原网站发布时间和要求为准。",
      "url": "http://www.zhaopin.com/jobdetail/CC486774830J40777351606.htm",
      "status": "auto"
    },
    {
      "id": "5efc0ad0fb4201e8",
      "major": "safety",
      "category": "job",
      "platform": "智联招聘",
      "source": "智联招聘",
      "title": "全国招聘体系认证预备/实习审核员专职兼职（免费培养有保底或补贴）",
      "summary": "来自 智联招聘 的安全工程相关实习/就业信息，请以原网站发布时间和要求为准。",
      "url": "http://www.zhaopin.com/jobdetail/CC120700450J40757854712.htm",
      "status": "auto"
    },
    {
      "id": "780aeaf2d130b3d4",
      "major": "safety",
      "category": "job",
      "platform": "智联招聘",
      "source": "智联招聘",
      "title": "数据标注（无经验，坐班，实习、社保）",
      "summary": "来自 智联招聘 的安全工程相关实习/就业信息，请以原网站发布时间和要求为准。",
      "url": "http://www.zhaopin.com/jobdetail/CC171774410J40680279314.htm",
      "status": "auto"
    },
    {
      "id": "69555257edfac02c",
      "major": "safety",
      "category": "job",
      "platform": "智联招聘",
      "source": "智联招聘",
      "title": "实习生-开发工程师(005619)",
      "summary": "来自 智联招聘 的安全工程相关实习/就业信息，请以原网站发布时间和要求为准。",
      "url": "http://www.zhaopin.com/jobdetail/CC000413680J40876339513.htm",
      "status": "auto"
    },
    {
      "id": "a06135970c3d3837",
      "major": "safety",
      "category": "job",
      "platform": "智联招聘",
      "source": "智联招聘",
      "title": "礼服走秀模特+包吃住+包妆造+实习证明",
      "summary": "来自 智联招聘 的安全工程相关实习/就业信息，请以原网站发布时间和要求为准。",
      "url": "http://www.zhaopin.com/jobdetail/CCL1520624210J40813076516.htm",
      "status": "auto"
    },
    {
      "id": "278bec16ade26f11",
      "major": "safety",
      "category": "job",
      "platform": "应届生求职网",
      "source": "应届生求职网",
      "title": "应届生求职网：EHS 实习",
      "summary": "该来源本次自动抓取受限，已保留公开搜索入口，方便用户进入原平台查看。",
      "url": "https://www.yingjiesheng.com/so.php?word=EHS%20%E5%AE%9E%E4%B9%A0",
      "status": "fallback"
    },
    {
      "id": "b7a0e39d27969cb5",
      "major": "safety",
      "category": "job",
      "platform": "实习僧",
      "source": "实习僧",
      "title": "&#xf1fb&#xe078&#xf0ab 实习&#xf16c-&#xf1fb&#xed1d",
      "summary": "来自 实习僧 的安全工程相关实习/就业信息，请以原网站发布时间和要求为准。",
      "url": "https://www.shixiseng.com/intern/inn_7dglctuszxmo?pcm=pc_SearchList",
      "status": "auto"
    },
    {
      "id": "9deca901f79606d6",
      "major": "safety",
      "category": "job",
      "platform": "实习僧",
      "source": "实习僧",
      "title": "&#xf1fb&#xe078&#xf0ab（环境健康安全）实习&#xf16c",
      "summary": "来自 实习僧 的安全工程相关实习/就业信息，请以原网站发布时间和要求为准。",
      "url": "https://www.shixiseng.com/intern/inn_fmrbeyrbgcki?pcm=pc_SearchList",
      "status": "auto"
    },
    {
      "id": "685abede22ee9ccb",
      "major": "safety",
      "category": "job",
      "platform": "智联招聘",
      "source": "智联招聘",
      "title": "HSE(实习)",
      "summary": "来自 智联招聘 的安全工程相关实习/就业信息，请以原网站发布时间和要求为准。",
      "url": "http://www.zhaopin.com/jobdetail/CC120502600J40768289206.htm",
      "status": "auto"
    },
    {
      "id": "a134de878f21da01",
      "major": "safety",
      "category": "job",
      "platform": "智联招聘",
      "source": "智联招聘",
      "title": "安全总监&HSE工程师",
      "summary": "来自 智联招聘 的安全工程相关公开信息，已按关键词自动归类。",
      "url": "http://www.zhaopin.com/jobdetail/CC208234980J40655386510.htm",
      "status": "auto"
    },
    {
      "id": "e655b1301351a424",
      "major": "safety",
      "category": "job",
      "platform": "智联招聘",
      "source": "智联招聘",
      "title": "HSE部门助理",
      "summary": "来自 智联招聘 的安全工程相关实习/就业信息，请以原网站发布时间和要求为准。",
      "url": "http://www.zhaopin.com/jobdetail/CC561929880J40861661609.htm",
      "status": "auto"
    },
    {
      "id": "70733703a4437e49",
      "major": "safety",
      "category": "job",
      "platform": "智联招聘",
      "source": "智联招聘",
      "title": "曼项目-HSE职业健康专员 J13834",
      "summary": "来自 智联招聘 的安全工程相关公开信息，已按关键词自动归类。",
      "url": "http://www.zhaopin.com/jobdetail/CC212499610J40901114203.htm",
      "status": "auto"
    },
    {
      "id": "4c4753e79b6eb82d",
      "major": "safety",
      "category": "job",
      "platform": "智联招聘",
      "source": "智联招聘",
      "title": "安全员/HSE经理",
      "summary": "来自 智联招聘 的安全工程相关公开信息，已按关键词自动归类。",
      "url": "http://www.zhaopin.com/jobdetail/CC369006614J90250830000.htm",
      "status": "auto"
    },
    {
      "id": "8215a4e06cb545ea",
      "major": "safety",
      "category": "job",
      "platform": "智联招聘",
      "source": "智联招聘",
      "title": "HSE部副经理（薪资面议）(J10178)",
      "summary": "来自 智联招聘 的安全工程相关公开信息，已按关键词自动归类。",
      "url": "http://www.zhaopin.com/jobdetail/CC171215710J40915884515.htm",
      "status": "auto"
    },
    {
      "id": "f4b3db8d713719e4",
      "major": "safety",
      "category": "job",
      "platform": "智联招聘",
      "source": "智联招聘",
      "title": "HSE 安全管理",
      "summary": "来自 智联招聘 的安全工程相关公开信息，已按关键词自动归类。",
      "url": "http://www.zhaopin.com/jobdetail/CC369006610J40623565214.htm",
      "status": "auto"
    },
    {
      "id": "7cd730cc7fcbf926",
      "major": "safety",
      "category": "job",
      "platform": "智联招聘",
      "source": "智联招聘",
      "title": "【防城港白龙核电】HSE监督管理岗",
      "summary": "来自 智联招聘 的安全工程相关公开信息，已按关键词自动归类。",
      "url": "http://www.zhaopin.com/jobdetail/CCL1478346110J40859404610.htm",
      "status": "auto"
    },
    {
      "id": "4d8df446ee7d3d18",
      "major": "safety",
      "category": "job",
      "platform": "智联招聘",
      "source": "智联招聘",
      "title": "核电-HSE监督管理岗",
      "summary": "来自 智联招聘 的安全工程相关公开信息，已按关键词自动归类。",
      "url": "http://www.zhaopin.com/jobdetail/CCL1478346110J40858440210.htm",
      "status": "auto"
    },
    {
      "id": "791d675c0b49278a",
      "major": "safety",
      "category": "job",
      "platform": "智联招聘",
      "source": "智联招聘",
      "title": "HSE工程师(J10990)",
      "summary": "来自 智联招聘 的安全工程相关公开信息，已按关键词自动归类。",
      "url": "http://www.zhaopin.com/jobdetail/CCL1379234130J40423051502.htm",
      "status": "auto"
    },
    {
      "id": "70a5da0e79f869d7",
      "major": "safety",
      "category": "job",
      "platform": "智联招聘",
      "source": "智联招聘",
      "title": "工艺与HSE工程师",
      "summary": "来自 智联招聘 的安全工程相关公开信息，已按关键词自动归类。",
      "url": "http://www.zhaopin.com/jobdetail/CCL1308319620J40911142615.htm",
      "status": "auto"
    },
    {
      "id": "a39b45700eea6a63",
      "major": "safety",
      "category": "job",
      "platform": "智联招聘",
      "source": "智联招聘",
      "title": "HSE安全管理员",
      "summary": "来自 智联招聘 的安全工程相关公开信息，已按关键词自动归类。",
      "url": "http://www.zhaopin.com/jobdetail/CC535834920J40772381610.htm",
      "status": "auto"
    },
    {
      "id": "adc739e76fe53451",
      "major": "safety",
      "category": "job",
      "platform": "应届生求职网",
      "source": "应届生求职网",
      "title": "应届生求职网：HSE 实习",
      "summary": "该来源本次自动抓取受限，已保留公开搜索入口，方便用户进入原平台查看。",
      "url": "https://www.yingjiesheng.com/so.php?word=HSE%20%E5%AE%9E%E4%B9%A0",
      "status": "fallback"
    },
    {
      "id": "036d239cc07294e0",
      "major": "safety",
      "category": "job",
      "platform": "实习僧",
      "source": "实习僧",
      "title": "基金评价实习&#xf16c",
      "summary": "来自 实习僧 的安全工程相关实习/就业信息，请以原网站发布时间和要求为准。",
      "url": "https://www.shixiseng.com/intern/inn_5jicjzdbylxq?pcm=pc_SearchList",
      "status": "auto"
    },
    {
      "id": "0e1a1ed28052bd0d",
      "major": "safety",
      "category": "job",
      "platform": "实习僧",
      "source": "实习僧",
      "title": "评价运营实习&#xf16c-抖音&#xf16c活服务",
      "summary": "来自 实习僧 的安全工程相关实习/就业信息，请以原网站发布时间和要求为准。",
      "url": "https://www.shixiseng.com/intern/inn_pcgxnuje2xfb?pcm=pc_SearchList",
      "status": "auto"
    },
    {
      "id": "6cbb7ad16f907367",
      "major": "safety",
      "category": "job",
      "platform": "实习僧",
      "source": "实习僧",
      "title": "安全测试实习&#xf16c",
      "summary": "来自 实习僧 的安全工程相关实习/就业信息，请以原网站发布时间和要求为准。",
      "url": "https://www.shixiseng.com/intern/inn_tuw56g3et9op?pcm=pc_SearchList",
      "status": "auto"
    },
    {
      "id": "f9928bafd668c51a",
      "major": "safety",
      "category": "job",
      "platform": "实习僧",
      "source": "实习僧",
      "title": "研发安全实习&#xf16c",
      "summary": "来自 实习僧 的安全工程相关实习/就业信息，请以原网站发布时间和要求为准。",
      "url": "https://www.shixiseng.com/intern/inn_silu0aeyfg33?pcm=pc_SearchList",
      "status": "auto"
    },
    {
      "id": "1ea5925cfa236cb3",
      "major": "safety",
      "category": "job",
      "platform": "实习僧",
      "source": "实习僧",
      "title": "安全研发实习&#xf16c",
      "summary": "来自 实习僧 的安全工程相关实习/就业信息，请以原网站发布时间和要求为准。",
      "url": "https://www.shixiseng.com/intern/inn_i2ep896yq1lk?pcm=pc_SearchList",
      "status": "auto"
    },
    {
      "id": "2d06106fbf481950",
      "major": "safety",
      "category": "job",
      "platform": "实习僧",
      "source": "实习僧",
      "title": "安全&#xe4e5&#xe4ec&#xe651（实习）",
      "summary": "来自 实习僧 的安全工程相关实习/就业信息，请以原网站发布时间和要求为准。",
      "url": "https://www.shixiseng.com/intern/inn_fhtivfczbnfm?pcm=pc_SearchList",
      "status": "auto"
    },
    {
      "id": "6c640a005d9eb2c1",
      "major": "safety",
      "category": "job",
      "platform": "智联招聘",
      "source": "智联招聘",
      "title": "消防中控（接受小白实习生）",
      "summary": "来自 智联招聘 的安全工程相关实习/就业信息，请以原网站发布时间和要求为准。",
      "url": "http://www.zhaopin.com/jobdetail/CCL1509989120J40805640805.htm",
      "status": "auto"
    },
    {
      "id": "bea3e2215aa26430",
      "major": "safety",
      "category": "job",
      "platform": "智联招聘",
      "source": "智联招聘",
      "title": "山东鲁轻安全评价技术有限公司",
      "summary": "来自 智联招聘 的安全工程相关公开信息，已按关键词自动归类。",
      "url": "https://www.zhaopin.com/companydetail/CZ460082730.htm",
      "status": "auto"
    },
    {
      "id": "08383f7bf0ac7e8d",
      "major": "safety",
      "category": "job",
      "platform": "智联招聘",
      "source": "智联招聘",
      "title": "安全服务工程师-SOC运营（可实习）",
      "summary": "来自 智联招聘 的安全工程相关实习/就业信息，请以原网站发布时间和要求为准。",
      "url": "http://www.zhaopin.com/jobdetail/CC380206280J40859506114.htm",
      "status": "auto"
    },
    {
      "id": "a8a17766e1cd2d82",
      "major": "safety",
      "category": "job",
      "platform": "智联招聘",
      "source": "智联招聘",
      "title": "消防中控（接受小白实习生",
      "summary": "来自 智联招聘 的安全工程相关实习/就业信息，请以原网站发布时间和要求为准。",
      "url": "http://www.zhaopin.com/jobdetail/CCL1509989120J40805640105.htm",
      "status": "auto"
    },
    {
      "id": "4eb023f216a7031e",
      "major": "safety",
      "category": "job",
      "platform": "智联招聘",
      "source": "智联招聘",
      "title": "嵌入式助理工程师(实习)",
      "summary": "来自 智联招聘 的安全工程相关实习/就业信息，请以原网站发布时间和要求为准。",
      "url": "http://www.zhaopin.com/jobdetail/CC287611980J40842014511.htm",
      "status": "auto"
    },
    {
      "id": "495a2ade7e36def4",
      "major": "safety",
      "category": "job",
      "platform": "智联招聘",
      "source": "智联招聘",
      "title": "消防中控（接受实习生",
      "summary": "来自 智联招聘 的安全工程相关实习/就业信息，请以原网站发布时间和要求为准。",
      "url": "http://www.zhaopin.com/jobdetail/CCL1509989120J40811128305.htm",
      "status": "auto"
    },
    {
      "id": "c2fcfe8a111745b2",
      "major": "safety",
      "category": "job",
      "platform": "智联招聘",
      "source": "智联招聘",
      "title": "网络安全工程师（实习生）",
      "summary": "来自 智联招聘 的安全工程相关实习/就业信息，请以原网站发布时间和要求为准。",
      "url": "http://www.zhaopin.com/jobdetail/CC265135120J40813451415.htm",
      "status": "auto"
    },
    {
      "id": "267eba3e3d77fb18",
      "major": "safety",
      "category": "job",
      "platform": "智联招聘",
      "source": "智联招聘",
      "title": "安全评价师（地点：甘肃）",
      "summary": "来自 智联招聘 的安全工程相关公开信息，已按关键词自动归类。",
      "url": "http://www.zhaopin.com/jobdetail/CC511863720J40552797507.htm",
      "status": "auto"
    },
    {
      "id": "252aa598a358207a",
      "major": "safety",
      "category": "job",
      "platform": "智联招聘",
      "source": "智联招聘",
      "title": "安全评价师（住建）",
      "summary": "来自 智联招聘 的安全工程相关公开信息，已按关键词自动归类。",
      "url": "http://www.zhaopin.com/jobdetail/CCL1414133040J40726183805.htm",
      "status": "auto"
    },
    {
      "id": "5546ee6b6ce6df72",
      "major": "safety",
      "category": "job",
      "platform": "智联招聘",
      "source": "智联招聘",
      "title": "实习生（2026-2027年毕业学生，化学、食品、环境相关专业）",
      "summary": "来自 智联招聘 的安全工程相关实习/就业信息，请以原网站发布时间和要求为准。",
      "url": "http://www.zhaopin.com/jobdetail/CC287611980J40774493911.htm",
      "status": "auto"
    },
    {
      "id": "8eab1567d6a4762d",
      "major": "safety",
      "category": "job",
      "platform": "智联招聘",
      "source": "智联招聘",
      "title": "安全评价师（石家庄）",
      "summary": "来自 智联招聘 的安全工程相关公开信息，已按关键词自动归类。",
      "url": "http://www.zhaopin.com/jobdetail/CC210815210J40931551415.htm",
      "status": "auto"
    },
    {
      "id": "fc83498637b6f2d2",
      "major": "safety",
      "category": "job",
      "platform": "应届生求职网",
      "source": "应届生求职网",
      "title": "应届生求职网：安全评价 实习",
      "summary": "该来源本次自动抓取受限，已保留公开搜索入口，方便用户进入原平台查看。",
      "url": "https://www.yingjiesheng.com/so.php?word=%E5%AE%89%E5%85%A8%E8%AF%84%E4%BB%B7%20%E5%AE%9E%E4%B9%A0",
      "status": "fallback"
    },
    {
      "id": "b53877854ccd6c73",
      "major": "safety",
      "category": "job",
      "platform": "智联招聘",
      "source": "智联招聘",
      "title": "网络安全工程设计（太原）",
      "summary": "来自 智联招聘 的安全工程相关公开信息，已按关键词自动归类。",
      "url": "http://www.zhaopin.com/jobdetail/CCL1288383070J40941708415.htm",
      "status": "auto"
    },
    {
      "id": "0ed1c70072818f35",
      "major": "safety",
      "category": "job",
      "platform": "应届生求职网",
      "source": "应届生求职网",
      "title": "应届生求职网：安全工程 面经",
      "summary": "该来源本次自动抓取受限，已保留公开搜索入口，方便用户进入原平台查看。",
      "url": "https://www.yingjiesheng.com/so.php?word=%E5%AE%89%E5%85%A8%E5%B7%A5%E7%A8%8B%20%E9%9D%A2%E7%BB%8F",
      "status": "fallback"
    },
    {
      "id": "373d5615a926fbe1",
      "major": "mining",
      "category": "job",
      "platform": "实习僧",
      "source": "实习僧",
      "title": "实习僧：采矿工程相关结果页",
      "summary": "已抓取到 实习僧 的公开搜索页，但页面结构限制了列表解析，请打开原页面查看最新结果。",
      "url": "https://www.shixiseng.com/interns?keyword=%E9%87%87%E7%9F%BF%E5%B7%A5%E7%A8%8B%20%E5%AE%9E%E4%B9%A0",
      "status": "search-page"
    },
    {
      "id": "942581057c07143e",
      "major": "mining",
      "category": "job",
      "platform": "智联招聘",
      "source": "智联招聘",
      "title": "采矿工程项目经理",
      "summary": "来自 智联招聘 的采矿工程相关公开信息，已按关键词自动归类。",
      "url": "http://www.zhaopin.com/jobdetail/CC645635180J40860462803.htm",
      "status": "auto"
    },
    {
      "id": "1566a9be81ecaef3",
      "major": "mining",
      "category": "job",
      "platform": "智联招聘",
      "source": "智联招聘",
      "title": "采矿工程专业大学生",
      "summary": "来自 智联招聘 的采矿工程相关公开信息，已按关键词自动归类。",
      "url": "http://www.zhaopin.com/jobdetail/CC660429520J40881048313.htm",
      "status": "auto"
    },
    {
      "id": "7cedbafb264cf2c5",
      "major": "mining",
      "category": "job",
      "platform": "智联招聘",
      "source": "智联招聘",
      "title": "大中矿业股份有限公司",
      "summary": "来自 智联招聘 的采矿工程相关公开信息，已按关键词自动归类。",
      "url": "https://www.zhaopin.com/companydetail/CZ660429520.htm",
      "status": "auto"
    },
    {
      "id": "ab35504f352a3adb",
      "major": "mining",
      "category": "job",
      "platform": "智联招聘",
      "source": "智联招聘",
      "title": "2025年-2026年校招——采矿工程岗",
      "summary": "来自 智联招聘 的采矿工程相关实习/就业信息，请以原网站发布时间和要求为准。",
      "url": "http://www.zhaopin.com/jobdetail/CC847037970J40629879713.htm",
      "status": "auto"
    },
    {
      "id": "76f46c9a4744ba88",
      "major": "mining",
      "category": "job",
      "platform": "智联招聘",
      "source": "智联招聘",
      "title": "海垦（陵水）建材公司矿山工程部采矿工程师",
      "summary": "来自 智联招聘 的采矿工程相关公开信息，已按关键词自动归类。",
      "url": "http://www.zhaopin.com/jobdetail/CC858511910J40753977615.htm",
      "status": "auto"
    },
    {
      "id": "1c6610e2e0be1330",
      "major": "mining",
      "category": "job",
      "platform": "智联招聘",
      "source": "智联招聘",
      "title": "采矿工程 工程师",
      "summary": "来自 智联招聘 的采矿工程相关公开信息，已按关键词自动归类。",
      "url": "http://www.zhaopin.com/jobdetail/CCL1200104590J40900031308.htm",
      "status": "auto"
    },
    {
      "id": "50b9d02501925daa",
      "major": "mining",
      "category": "job",
      "platform": "智联招聘",
      "source": "智联招聘",
      "title": "鞍钢集团矿业设计研究院有限公司",
      "summary": "来自 智联招聘 的采矿工程相关公开信息，已按关键词自动归类。",
      "url": "https://www.zhaopin.com/companydetail/CZL1200104590.htm",
      "status": "auto"
    },
    {
      "id": "be8f4ea4e11611e9",
      "major": "mining",
      "category": "job",
      "platform": "智联招聘",
      "source": "智联招聘",
      "title": "采矿工程设计技术人员",
      "summary": "来自 智联招聘 的采矿工程相关公开信息，已按关键词自动归类。",
      "url": "http://www.zhaopin.com/jobdetail/CC346810610J40830131710.htm",
      "status": "auto"
    },
    {
      "id": "5d4a55c2fcc20c53",
      "major": "mining",
      "category": "job",
      "platform": "智联招聘",
      "source": "智联招聘",
      "title": "长沙矿山研究院有限责任公司",
      "summary": "来自 智联招聘 的采矿工程相关公开信息，已按关键词自动归类。",
      "url": "https://www.zhaopin.com/companydetail/CZ173653510.htm",
      "status": "auto"
    },
    {
      "id": "0d28bc9852756d5b",
      "major": "mining",
      "category": "job",
      "platform": "前程无忧",
      "source": "前程无忧",
      "title": "前程无忧：采矿工程相关结果页",
      "summary": "已抓取到 前程无忧 的公开搜索页，但页面结构限制了列表解析，请打开原页面查看最新结果。",
      "url": "https://we.51job.com/pc/search?keyword=%E9%87%87%E7%9F%BF%E5%B7%A5%E7%A8%8B%20%E5%AE%9E%E4%B9%A0",
      "status": "search-page"
    },
    {
      "id": "feee776e89a2c2a2",
      "major": "mining",
      "category": "job",
      "platform": "应届生求职网",
      "source": "应届生求职网",
      "title": "应届生求职网：采矿工程 实习",
      "summary": "该来源本次自动抓取受限，已保留公开搜索入口，方便用户进入原平台查看。",
      "url": "https://www.yingjiesheng.com/so.php?word=%E9%87%87%E7%9F%BF%E5%B7%A5%E7%A8%8B%20%E5%AE%9E%E4%B9%A0",
      "status": "fallback"
    },
    {
      "id": "0f75427d8c54b23d",
      "major": "mining",
      "category": "job",
      "platform": "猎聘",
      "source": "猎聘",
      "title": "混凝土业务员招聘",
      "summary": "来自 猎聘 的采矿工程相关实习/就业信息，请以原网站发布时间和要求为准。",
      "url": "https://www.liepin.com/zphntywy6l6w/",
      "status": "auto"
    },
    {
      "id": "b06efec66784d541",
      "major": "mining",
      "category": "job",
      "platform": "猎聘",
      "source": "猎聘",
      "title": "冰吧企划经理招聘",
      "summary": "来自 猎聘 的采矿工程相关实习/就业信息，请以原网站发布时间和要求为准。",
      "url": "https://www.liepin.com/zpbbqhjl4p4w/",
      "status": "auto"
    },
    {
      "id": "4f7faf6d46016f90",
      "major": "mining",
      "category": "job",
      "platform": "猎聘",
      "source": "猎聘",
      "title": "插画设计导师招聘",
      "summary": "来自 猎聘 的采矿工程相关实习/就业信息，请以原网站发布时间和要求为准。",
      "url": "https://www.liepin.com/zpchsjds2w3o/",
      "status": "auto"
    },
    {
      "id": "969082386f3943e4",
      "major": "mining",
      "category": "job",
      "platform": "猎聘",
      "source": "猎聘",
      "title": "拎包设计主管招聘",
      "summary": "来自 猎聘 的采矿工程相关实习/就业信息，请以原网站发布时间和要求为准。",
      "url": "https://www.liepin.com/zplbsjzg8a1u/",
      "status": "auto"
    },
    {
      "id": "ea8951b916622421",
      "major": "mining",
      "category": "job",
      "platform": "猎聘",
      "source": "猎聘",
      "title": "资深数据风控招聘",
      "summary": "来自 猎聘 的采矿工程相关实习/就业信息，请以原网站发布时间和要求为准。",
      "url": "https://www.liepin.com/zpzssjfk3j5t/",
      "status": "auto"
    },
    {
      "id": "17eb9facf4929ee7",
      "major": "mining",
      "category": "job",
      "platform": "猎聘",
      "source": "猎聘",
      "title": "足疗推拿技师招聘",
      "summary": "来自 猎聘 的采矿工程相关实习/就业信息，请以原网站发布时间和要求为准。",
      "url": "https://www.liepin.com/zpzltnjs3a6s/",
      "status": "auto"
    },
    {
      "id": "adecbb5e8488b2cd",
      "major": "mining",
      "category": "job",
      "platform": "猎聘",
      "source": "猎聘",
      "title": "高级销售推广招聘",
      "summary": "来自 猎聘 的采矿工程相关实习/就业信息，请以原网站发布时间和要求为准。",
      "url": "https://www.liepin.com/zpgjxstg1t5y/",
      "status": "auto"
    },
    {
      "id": "f5decce4388440f5",
      "major": "mining",
      "category": "job",
      "platform": "猎聘",
      "source": "猎聘",
      "title": "家具建材仓库管理招聘",
      "summary": "来自 猎聘 的采矿工程相关实习/就业信息，请以原网站发布时间和要求为准。",
      "url": "https://www.liepin.com/zpjjjcckgl6f5a/",
      "status": "auto"
    },
    {
      "id": "94b7160150279942",
      "major": "mining",
      "category": "job",
      "platform": "猎聘",
      "source": "猎聘",
      "title": "水电气规划工程师招聘",
      "summary": "来自 猎聘 的采矿工程相关实习/就业信息，请以原网站发布时间和要求为准。",
      "url": "https://www.liepin.com/zpsdqghgcs6x2g/",
      "status": "auto"
    },
    {
      "id": "d4b8072576a14aab",
      "major": "mining",
      "category": "job",
      "platform": "猎聘",
      "source": "猎聘",
      "title": "外贸理单主管招聘",
      "summary": "来自 猎聘 的采矿工程相关实习/就业信息，请以原网站发布时间和要求为准。",
      "url": "https://www.liepin.com/zpwmldzgf4t7/",
      "status": "auto"
    },
    {
      "id": "d74f7dbef33313f1",
      "major": "mining",
      "category": "job",
      "platform": "猎聘",
      "source": "猎聘",
      "title": "欧洲GTM总监招聘",
      "summary": "来自 猎聘 的采矿工程相关实习/就业信息，请以原网站发布时间和要求为准。",
      "url": "https://www.liepin.com/zpozgtmzj9m4t/",
      "status": "auto"
    },
    {
      "id": "f62a5c5820fac610",
      "major": "mining",
      "category": "job",
      "platform": "猎聘",
      "source": "猎聘",
      "title": "跟单客服专员CSR招聘",
      "summary": "来自 猎聘 的采矿工程相关实习/就业信息，请以原网站发布时间和要求为准。",
      "url": "https://www.liepin.com/zpgdkfzycsr1v8p/",
      "status": "auto"
    },
    {
      "id": "c3c56f4dc43c3430",
      "major": "mining",
      "category": "social",
      "platform": "Bilibili",
      "source": "Bilibili",
      "title": "Bilibili：采矿工程相关结果页",
      "summary": "已抓取到 Bilibili 的公开搜索页，但页面结构限制了列表解析，请打开原页面查看最新结果。",
      "url": "https://search.bilibili.com/all?keyword=%E9%87%87%E7%9F%BF%E5%B7%A5%E7%A8%8B%20%E5%AE%9E%E4%B9%A0",
      "status": "search-page"
    },
    {
      "id": "6b66b6d43cc93e42",
      "major": "mining",
      "category": "social",
      "platform": "小红书",
      "source": "小红书",
      "title": "小红书：采矿工程相关结果页",
      "summary": "已抓取到 小红书 的公开搜索页，但页面结构限制了列表解析，请打开原页面查看最新结果。",
      "url": "https://www.xiaohongshu.com/search_result?keyword=%E9%87%87%E7%9F%BF%E5%B7%A5%E7%A8%8B%20%E5%AE%9E%E4%B9%A0",
      "status": "search-page"
    },
    {
      "id": "4cd6ea3439380531",
      "major": "mining",
      "category": "job",
      "platform": "智联招聘",
      "source": "智联招聘",
      "title": "西藏集为矿山运营股份有限公司",
      "summary": "来自 智联招聘 的采矿工程相关公开信息，已按关键词自动归类。",
      "url": "https://www.zhaopin.com/companydetail/CZ319197230.htm",
      "status": "auto"
    },
    {
      "id": "4b35998ecf4370e0",
      "major": "mining",
      "category": "job",
      "platform": "智联招聘",
      "source": "智联招聘",
      "title": "沈阳海纳森矿山机械有限公司",
      "summary": "来自 智联招聘 的采矿工程相关公开信息，已按关键词自动归类。",
      "url": "https://www.zhaopin.com/companydetail/CZL1481670230.htm",
      "status": "auto"
    },
    {
      "id": "edf956b5d6720305",
      "major": "mining",
      "category": "job",
      "platform": "智联招聘",
      "source": "智联招聘",
      "title": "销售经理 （榆林市）煤炭行业 矿山设备销售",
      "summary": "来自 智联招聘 的采矿工程相关公开信息，已按关键词自动归类。",
      "url": "http://www.zhaopin.com/jobdetail/CC495518880J40472643814.htm",
      "status": "auto"
    },
    {
      "id": "e7b13389d8af2bbf",
      "major": "mining",
      "category": "job",
      "platform": "智联招聘",
      "source": "智联招聘",
      "title": "徐州中矿汇弘矿山设备有限公司",
      "summary": "来自 智联招聘 的采矿工程相关公开信息，已按关键词自动归类。",
      "url": "https://www.zhaopin.com/companydetail/CC495518883.htm",
      "status": "auto"
    },
    {
      "id": "af6c5ba6f0d719c0",
      "major": "mining",
      "category": "job",
      "platform": "智联招聘",
      "source": "智联招聘",
      "title": "矿山装备结构设计",
      "summary": "来自 智联招聘 的采矿工程相关公开信息，已按关键词自动归类。",
      "url": "http://www.zhaopin.com/jobdetail/CC173653510J40783627305.htm",
      "status": "auto"
    },
    {
      "id": "3a81c0a08083734a",
      "major": "mining",
      "category": "job",
      "platform": "智联招聘",
      "source": "智联招聘",
      "title": "矿山设备销售专员",
      "summary": "来自 智联招聘 的采矿工程相关公开信息，已按关键词自动归类。",
      "url": "http://www.zhaopin.com/jobdetail/CCL1481670230J40676388606.htm",
      "status": "auto"
    },
    {
      "id": "7d44ceed74b685ef",
      "major": "mining",
      "category": "job",
      "platform": "智联招聘",
      "source": "智联招聘",
      "title": "陕西国鑫矿山工程有限公司",
      "summary": "来自 智联招聘 的采矿工程相关公开信息，已按关键词自动归类。",
      "url": "https://www.zhaopin.com/companydetail/CZL1513459230.htm",
      "status": "auto"
    },
    {
      "id": "d86883bbc7927bef",
      "major": "mining",
      "category": "job",
      "platform": "应届生求职网",
      "source": "应届生求职网",
      "title": "应届生求职网：矿山 实习",
      "summary": "该来源本次自动抓取受限，已保留公开搜索入口，方便用户进入原平台查看。",
      "url": "https://www.yingjiesheng.com/so.php?word=%E7%9F%BF%E5%B1%B1%20%E5%AE%9E%E4%B9%A0",
      "status": "fallback"
    },
    {
      "id": "b933a9dc1df9ff8e",
      "major": "mining",
      "category": "job",
      "platform": "实习僧",
      "source": "实习僧",
      "title": "智能研究组实习&#xf16c",
      "summary": "来自 实习僧 的采矿工程相关实习/就业信息，请以原网站发布时间和要求为准。",
      "url": "https://www.shixiseng.com/intern/inn_zxtuoan2wrse?pcm=pc_SearchList",
      "status": "auto"
    },
    {
      "id": "38914ab0b038faf6",
      "major": "mining",
      "category": "job",
      "platform": "实习僧",
      "source": "实习僧",
      "title": "具身智能实习&#xf16c",
      "summary": "来自 实习僧 的采矿工程相关实习/就业信息，请以原网站发布时间和要求为准。",
      "url": "https://www.shixiseng.com/intern/inn_binngf4kj4oa?pcm=pc_SearchList",
      "status": "auto"
    },
    {
      "id": "ab4ee3c472b9e3e0",
      "major": "mining",
      "category": "job",
      "platform": "实习僧",
      "source": "实习僧",
      "title": "智能编码实习&#xf16c",
      "summary": "来自 实习僧 的采矿工程相关实习/就业信息，请以原网站发布时间和要求为准。",
      "url": "https://www.shixiseng.com/intern/inn_mfv78h4vf1f0?pcm=pc_SearchList",
      "status": "auto"
    },
    {
      "id": "7ee500ad4c0b0adc",
      "major": "mining",
      "category": "job",
      "platform": "实习僧",
      "source": "实习僧",
      "title": "智能制造实习&#xf16c",
      "summary": "来自 实习僧 的采矿工程相关实习/就业信息，请以原网站发布时间和要求为准。",
      "url": "https://www.shixiseng.com/intern/inn_85ntfidsr2vw?pcm=pc_SearchList",
      "status": "auto"
    },
    {
      "id": "1eb07bbd48c6ecc4",
      "major": "mining",
      "category": "job",
      "platform": "实习僧",
      "source": "实习僧",
      "title": "&#xf1cc&#xe4fb智能测试战略实习&#xf16c——智能制造领域",
      "summary": "来自 实习僧 的采矿工程相关实习/就业信息，请以原网站发布时间和要求为准。",
      "url": "https://www.shixiseng.com/intern/inn_jgx7peifyj7t?pcm=pc_SearchList",
      "status": "auto"
    },
    {
      "id": "d3a2f79b2bbda22f",
      "major": "mining",
      "category": "job",
      "platform": "实习僧",
      "source": "实习僧",
      "title": "&#xf1cc&#xe4fb视觉与智能检测战略实习&#xf16c——智能制造领域",
      "summary": "来自 实习僧 的采矿工程相关实习/就业信息，请以原网站发布时间和要求为准。",
      "url": "https://www.shixiseng.com/intern/inn_8yyblqzpby36?pcm=pc_SearchList",
      "status": "auto"
    },
    {
      "id": "e166481c30a345d1",
      "major": "mining",
      "category": "job",
      "platform": "实习僧",
      "source": "实习僧",
      "title": "具身智能算法实习&#xf16c",
      "summary": "来自 实习僧 的采矿工程相关实习/就业信息，请以原网站发布时间和要求为准。",
      "url": "https://www.shixiseng.com/intern/inn_ibsqnhte3vgh?pcm=pc_SearchList",
      "status": "auto"
    },
    {
      "id": "c7f9511d14e863a0",
      "major": "mining",
      "category": "job",
      "platform": "实习僧",
      "source": "实习僧",
      "title": "消费者智能运营实习&#xf16c",
      "summary": "来自 实习僧 的采矿工程相关实习/就业信息，请以原网站发布时间和要求为准。",
      "url": "https://www.shixiseng.com/intern/inn_mgcejdppcpyq?pcm=pc_SearchList",
      "status": "auto"
    },
    {
      "id": "9183791a4c0e6c97",
      "major": "mining",
      "category": "job",
      "platform": "实习僧",
      "source": "实习僧",
      "title": "空间智能算法实习&#xf16c",
      "summary": "来自 实习僧 的采矿工程相关实习/就业信息，请以原网站发布时间和要求为准。",
      "url": "https://www.shixiseng.com/intern/inn_opitjicpmzj9?pcm=pc_SearchList",
      "status": "auto"
    },
    {
      "id": "be40d8aa34c690f3",
      "major": "mining",
      "category": "job",
      "platform": "实习僧",
      "source": "实习僧",
      "title": "智能体测试实习&#xf16c",
      "summary": "来自 实习僧 的采矿工程相关实习/就业信息，请以原网站发布时间和要求为准。",
      "url": "https://www.shixiseng.com/intern/inn_4aryam6be4nt?pcm=pc_SearchList",
      "status": "auto"
    },
    {
      "id": "c2c1155441d5130b",
      "major": "mining",
      "category": "job",
      "platform": "智联招聘",
      "source": "智联招聘",
      "title": "机器视觉工程师实习生",
      "summary": "来自 智联招聘 的采矿工程相关实习/就业信息，请以原网站发布时间和要求为准。",
      "url": "http://www.zhaopin.com/jobdetail/CC166275810J40898561503.htm",
      "status": "auto"
    },
    {
      "id": "2aaa4d550aa5bfdf",
      "major": "mining",
      "category": "job",
      "platform": "智联招聘",
      "source": "智联招聘",
      "title": "产品设计/工业设计实习生【基地入孵企业岗位】",
      "summary": "来自 智联招聘 的采矿工程相关实习/就业信息，请以原网站发布时间和要求为准。",
      "url": "http://www.zhaopin.com/jobdetail/CCL1372871170J40621894207.htm",
      "status": "auto"
    },
    {
      "id": "b240779fb42268e0",
      "major": "mining",
      "category": "job",
      "platform": "智联招聘",
      "source": "智联招聘",
      "title": "人事实习生(2027年后毕业)",
      "summary": "来自 智联招聘 的采矿工程相关实习/就业信息，请以原网站发布时间和要求为准。",
      "url": "http://www.zhaopin.com/jobdetail/CCL1507603100J40899727603.htm",
      "status": "auto"
    },
    {
      "id": "06cb12df80c29cac",
      "major": "mining",
      "category": "job",
      "platform": "智联招聘",
      "source": "智联招聘",
      "title": "嵌入式软件工程师（实习）",
      "summary": "来自 智联招聘 的采矿工程相关实习/就业信息，请以原网站发布时间和要求为准。",
      "url": "http://www.zhaopin.com/jobdetail/CCL1478427570J40853452311.htm",
      "status": "auto"
    },
    {
      "id": "11283c71c13fba70",
      "major": "mining",
      "category": "job",
      "platform": "智联招聘",
      "source": "智联招聘",
      "title": "机器人实习生（上海）",
      "summary": "来自 智联招聘 的采矿工程相关实习/就业信息，请以原网站发布时间和要求为准。",
      "url": "http://www.zhaopin.com/jobdetail/CC846487160J40417091107.htm",
      "status": "auto"
    },
    {
      "id": "11b09ae9c45ffa9c",
      "major": "mining",
      "category": "job",
      "platform": "智联招聘",
      "source": "智联招聘",
      "title": "机器人上位机软件工程师（实习岗）",
      "summary": "来自 智联招聘 的采矿工程相关实习/就业信息，请以原网站发布时间和要求为准。",
      "url": "http://www.zhaopin.com/jobdetail/CC300880130J40718185116.htm",
      "status": "auto"
    },
    {
      "id": "c5c4fd5235046ef5",
      "major": "mining",
      "category": "job",
      "platform": "智联招聘",
      "source": "智联招聘",
      "title": "硬件工程师实习生",
      "summary": "来自 智联招聘 的采矿工程相关实习/就业信息，请以原网站发布时间和要求为准。",
      "url": "http://www.zhaopin.com/jobdetail/CC301565530J40864824913.htm",
      "status": "auto"
    },
    {
      "id": "b1f90b4687c3c000",
      "major": "mining",
      "category": "job",
      "platform": "智联招聘",
      "source": "智联招聘",
      "title": "工业机器人调试储备人才（接受应届生/实习生）",
      "summary": "来自 智联招聘 的采矿工程相关实习/就业信息，请以原网站发布时间和要求为准。",
      "url": "http://www.zhaopin.com/jobdetail/CCL1441972650J40504149304.htm",
      "status": "auto"
    },
    {
      "id": "a38a7ff767b562a6",
      "major": "mining",
      "category": "job",
      "platform": "智联招聘",
      "source": "智联招聘",
      "title": "财务实习生(J16293)",
      "summary": "来自 智联招聘 的采矿工程相关实习/就业信息，请以原网站发布时间和要求为准。",
      "url": "http://www.zhaopin.com/jobdetail/CC166275810J40898263003.htm",
      "status": "auto"
    },
    {
      "id": "7097d4778cfb1d0e",
      "major": "mining",
      "category": "job",
      "platform": "智联招聘",
      "source": "智联招聘",
      "title": "环境分析检测-实习（2027届毕业生）",
      "summary": "来自 智联招聘 的采矿工程相关实习/就业信息，请以原网站发布时间和要求为准。",
      "url": "http://www.zhaopin.com/jobdetail/CC142200220J40435198908.htm",
      "status": "auto"
    },
    {
      "id": "ea6f9fea1f01ca81",
      "major": "mining",
      "category": "job",
      "platform": "智联招聘",
      "source": "智联招聘",
      "title": "编辑（线上实习）",
      "summary": "来自 智联招聘 的采矿工程相关实习/就业信息，请以原网站发布时间和要求为准。",
      "url": "http://www.zhaopin.com/jobdetail/CC284761780J40589022109.htm",
      "status": "auto"
    },
    {
      "id": "0d20abe6e9215d7e",
      "major": "mining",
      "category": "job",
      "platform": "智联招聘",
      "source": "智联招聘",
      "title": "设备管理实习生（可实习半年以上）",
      "summary": "来自 智联招聘 的采矿工程相关实习/就业信息，请以原网站发布时间和要求为准。",
      "url": "http://www.zhaopin.com/jobdetail/CC142200220J40272797308.htm",
      "status": "auto"
    },
    {
      "id": "6f778d4238ca77ee",
      "major": "mining",
      "category": "job",
      "platform": "应届生求职网",
      "source": "应届生求职网",
      "title": "应届生求职网：智能矿山 实习",
      "summary": "该来源本次自动抓取受限，已保留公开搜索入口，方便用户进入原平台查看。",
      "url": "https://www.yingjiesheng.com/so.php?word=%E6%99%BA%E8%83%BD%E7%9F%BF%E5%B1%B1%20%E5%AE%9E%E4%B9%A0",
      "status": "fallback"
    },
    {
      "id": "cc28044ebaf0bf36",
      "major": "mining",
      "category": "job",
      "platform": "应届生求职网",
      "source": "应届生求职网",
      "title": "应届生求职网：采矿工程 面经",
      "summary": "该来源本次自动抓取受限，已保留公开搜索入口，方便用户进入原平台查看。",
      "url": "https://www.yingjiesheng.com/so.php?word=%E9%87%87%E7%9F%BF%E5%B7%A5%E7%A8%8B%20%E9%9D%A2%E7%BB%8F",
      "status": "fallback"
    },
    {
      "id": "a261f7adc89c2966",
      "major": "mining",
      "category": "job",
      "platform": "实习僧",
      "source": "实习僧",
      "title": "新媒体实习&#xf16c（校&#xe631）",
      "summary": "来自 实习僧 的采矿工程相关实习/就业信息，请以原网站发布时间和要求为准。",
      "url": "https://www.shixiseng.com/intern/inn_9izeacxhrh82?pcm=pc_SearchList",
      "status": "auto"
    },
    {
      "id": "5b500299828bab86",
      "major": "mining",
      "category": "job",
      "platform": "实习僧",
      "source": "实习僧",
      "title": "&#xe079&#xe37e&#xe078开发实习&#xf16c（校&#xe631）",
      "summary": "来自 实习僧 的采矿工程相关实习/就业信息，请以原网站发布时间和要求为准。",
      "url": "https://www.shixiseng.com/intern/inn_zkv4fdwsb68d?pcm=pc_SearchList",
      "status": "auto"
    },
    {
      "id": "551dc3e280cd18db",
      "major": "mining",
      "category": "job",
      "platform": "实习僧",
      "source": "实习僧",
      "title": "&#xf1cc&#xf82b&#xe039&#xf09d&#xe893&#xe079&#xe039开发实习&#xf16c（校&#xe631）",
      "summary": "来自 实习僧 的采矿工程相关实习/就业信息，请以原网站发布时间和要求为准。",
      "url": "https://www.shixiseng.com/intern/inn_p85wmlotvgd7?pcm=pc_SearchList",
      "status": "auto"
    },
    {
      "id": "56ae7c537acb9353",
      "major": "mining",
      "category": "job",
      "platform": "实习僧",
      "source": "实习僧",
      "title": "&#xf0fc力资源部校&#xe631团队实习&#xf16c-上海",
      "summary": "来自 实习僧 的采矿工程相关实习/就业信息，请以原网站发布时间和要求为准。",
      "url": "https://www.shixiseng.com/intern/inn_noq2n1ia9gtj?pcm=pc_SearchList",
      "status": "auto"
    },
    {
      "id": "a3d6e438f179b127",
      "major": "mining",
      "category": "job",
      "platform": "实习僧",
      "source": "实习僧",
      "title": "【校&#xe631】医药代表实习&#xf16c-通辽",
      "summary": "来自 实习僧 的采矿工程相关实习/就业信息，请以原网站发布时间和要求为准。",
      "url": "https://www.shixiseng.com/intern/inn_bzc4a40klynd?pcm=pc_SearchList",
      "status": "auto"
    },
    {
      "id": "f01e8ccd8c7473f0",
      "major": "mining",
      "category": "job",
      "platform": "实习僧",
      "source": "实习僧",
      "title": "校&#xe631-医药大模型实习&#xf16c(&#xf1cc&#xf2df&#xf2df&#xf1e5&#xf55d&#xf754)",
      "summary": "来自 实习僧 的采矿工程相关实习/就业信息，请以原网站发布时间和要求为准。",
      "url": "https://www.shixiseng.com/intern/inn_yk1fwrr5yncs?pcm=pc_SearchList",
      "status": "auto"
    },
    {
      "id": "6e90e04ce5b90fae",
      "major": "mining",
      "category": "job",
      "platform": "实习僧",
      "source": "实习僧",
      "title": "量化实习&#xf16c（&#xee4e&#xe079&#xf82b&#xf110&#xe9d3 &#xf69b&#xf400&#xf110&#xf09d校&#xe631）",
      "summary": "来自 实习僧 的采矿工程相关实习/就业信息，请以原网站发布时间和要求为准。",
      "url": "https://www.shixiseng.com/intern/inn_nmbwrdiskpqx?pcm=pc_SearchList",
      "status": "auto"
    },
    {
      "id": "0634970a6be00857",
      "major": "mining",
      "category": "job",
      "platform": "实习僧",
      "source": "实习僧",
      "title": "【&#xe53c&#xf76f&#xe53c&#xf754校&#xe631暑期实习】后&#xf702&#xe4e5&#xe4ec&#xe651",
      "summary": "来自 实习僧 的采矿工程相关实习/就业信息，请以原网站发布时间和要求为准。",
      "url": "https://www.shixiseng.com/intern/inn_wy6celsb6vuj?pcm=pc_SearchList",
      "status": "auto"
    },
    {
      "id": "f1479161212060d0",
      "major": "mining",
      "category": "job",
      "platform": "智联招聘",
      "source": "智联招聘",
      "title": "地质/采矿/测量/技术员（锐能矿业）",
      "summary": "来自 智联招聘 的采矿工程相关公开信息，已按关键词自动归类。",
      "url": "http://www.zhaopin.com/jobdetail/CC540556320J40891816412.htm",
      "status": "auto"
    },
    {
      "id": "f44069062103f8f4",
      "major": "mining",
      "category": "job",
      "platform": "智联招聘",
      "source": "智联招聘",
      "title": "内蒙古兴业银锡矿业股份有限公司",
      "summary": "来自 智联招聘 的采矿工程相关公开信息，已按关键词自动归类。",
      "url": "https://www.zhaopin.com/companydetail/CC540556323.htm",
      "status": "auto"
    },
    {
      "id": "6abbde61c3e1cebc",
      "major": "mining",
      "category": "job",
      "platform": "智联招聘",
      "source": "智联招聘",
      "title": "雷波县华瑞矿业有限公司",
      "summary": "来自 智联招聘 的采矿工程相关公开信息，已按关键词自动归类。",
      "url": "https://www.zhaopin.com/companydetail/CZL1461826560.htm",
      "status": "auto"
    },
    {
      "id": "ab9a6a5c7d444122",
      "major": "mining",
      "category": "job",
      "platform": "智联招聘",
      "source": "智联招聘",
      "title": "副总工程师（矿业开发）",
      "summary": "来自 智联招聘 的采矿工程相关公开信息，已按关键词自动归类。",
      "url": "http://www.zhaopin.com/jobdetail/CCL1390606780J40852841014.htm",
      "status": "auto"
    },
    {
      "id": "c6a0d93c7e7835d1",
      "major": "mining",
      "category": "job",
      "platform": "智联招聘",
      "source": "智联招聘",
      "title": "新疆天地源矿业集团有限公司",
      "summary": "来自 智联招聘 的采矿工程相关公开信息，已按关键词自动归类。",
      "url": "https://www.zhaopin.com/companydetail/CZL1390606780.htm",
      "status": "auto"
    },
    {
      "id": "f1968b307c15cbdf",
      "major": "mining",
      "category": "job",
      "platform": "智联招聘",
      "source": "智联招聘",
      "title": "山东磐久矿业有限公司",
      "summary": "来自 智联招聘 的采矿工程相关公开信息，已按关键词自动归类。",
      "url": "https://www.zhaopin.com/companydetail/CZL1493198800.htm",
      "status": "auto"
    },
    {
      "id": "a1fcddbdc1ff11a0",
      "major": "mining",
      "category": "job",
      "platform": "智联招聘",
      "source": "智联招聘",
      "title": "矿业选厂资深机电工程师",
      "summary": "来自 智联招聘 的采矿工程相关公开信息，已按关键词自动归类。",
      "url": "http://www.zhaopin.com/jobdetail/CC190868810J40995536004.htm",
      "status": "auto"
    },
    {
      "id": "4581ee53eb4ad9f1",
      "major": "mining",
      "category": "job",
      "platform": "智联招聘",
      "source": "智联招聘",
      "title": "河南发恩德矿业有限公司",
      "summary": "来自 智联招聘 的采矿工程相关公开信息，已按关键词自动归类。",
      "url": "https://www.zhaopin.com/companydetail/CZ190868810.htm",
      "status": "auto"
    },
    {
      "id": "37dc482580d4ba33",
      "major": "mining",
      "category": "job",
      "platform": "智联招聘",
      "source": "智联招聘",
      "title": "锡林郭勒盟隆兴矿业有限责任公司",
      "summary": "来自 智联招聘 的采矿工程相关公开信息，已按关键词自动归类。",
      "url": "https://www.zhaopin.com/companydetail/CZ692746080.htm",
      "status": "auto"
    },
    {
      "id": "ac965bb2cc646772",
      "major": "mining",
      "category": "job",
      "platform": "智联招聘",
      "source": "智联招聘",
      "title": "矿业产业发展研究副主任（主持工作）",
      "summary": "来自 智联招聘 的采矿工程相关公开信息，已按关键词自动归类。",
      "url": "http://www.zhaopin.com/jobdetail/CCL1391678980J40857063014.htm",
      "status": "auto"
    },
    {
      "id": "3f546649bc135313",
      "major": "mining",
      "category": "job",
      "platform": "智联招聘",
      "source": "智联招聘",
      "title": "四川省天府矿业投资有限责任公司",
      "summary": "来自 智联招聘 的采矿工程相关公开信息，已按关键词自动归类。",
      "url": "https://www.zhaopin.com/companydetail/CZL1391678980.htm",
      "status": "auto"
    },
    {
      "id": "d96fa8e3554e2b38",
      "major": "mining",
      "category": "job",
      "platform": "智联招聘",
      "source": "智联招聘",
      "title": "矿业公司主管会计",
      "summary": "来自 智联招聘 的采矿工程相关公开信息，已按关键词自动归类。",
      "url": "http://www.zhaopin.com/jobdetail/CCL1389386260J40864368010.htm",
      "status": "auto"
    },
    {
      "id": "2cce0e7fef05525e",
      "major": "mining",
      "category": "job",
      "platform": "应届生求职网",
      "source": "应届生求职网",
      "title": "应届生求职网：矿业 校招",
      "summary": "该来源本次自动抓取受限，已保留公开搜索入口，方便用户进入原平台查看。",
      "url": "https://www.yingjiesheng.com/so.php?word=%E7%9F%BF%E4%B8%9A%20%E6%A0%A1%E6%8B%9B",
      "status": "fallback"
    },
    {
      "id": "45c17577a084bd0f",
      "major": "underground",
      "category": "job",
      "platform": "实习僧",
      "source": "实习僧",
      "title": "&#xee66务部实习&#xf16c",
      "summary": "来自 实习僧 的城市地下空间工程相关实习/就业信息，请以原网站发布时间和要求为准。",
      "url": "https://www.shixiseng.com/intern/inn_jrcvmwcebme4?pcm=pc_SearchList",
      "status": "auto"
    },
    {
      "id": "e5af5cae2f9c1566",
      "major": "underground",
      "category": "job",
      "platform": "实习僧",
      "source": "实习僧",
      "title": "&#xee66务实习&#xf16c",
      "summary": "来自 实习僧 的城市地下空间工程相关实习/就业信息，请以原网站发布时间和要求为准。",
      "url": "https://www.shixiseng.com/intern/inn_xdlkzdbbykwd?pcm=pc_SearchList",
      "status": "auto"
    },
    {
      "id": "fdddfd29bdf9891e",
      "major": "underground",
      "category": "job",
      "platform": "实习僧",
      "source": "实习僧",
      "title": "&#xe4fb&#xe747实习&#xf16c",
      "summary": "来自 实习僧 的城市地下空间工程相关实习/就业信息，请以原网站发布时间和要求为准。",
      "url": "https://www.shixiseng.com/intern/inn_2sfjksjmwxoa?pcm=pc_SearchList",
      "status": "auto"
    },
    {
      "id": "86ea5f728ea02087",
      "major": "underground",
      "category": "job",
      "platform": "实习僧",
      "source": "实习僧",
      "title": "文员实习&#xf16c",
      "summary": "来自 实习僧 的城市地下空间工程相关实习/就业信息，请以原网站发布时间和要求为准。",
      "url": "https://www.shixiseng.com/intern/inn_abgi6vflpspe?pcm=pc_SearchList",
      "status": "auto"
    },
    {
      "id": "02414ec3ddc10e50",
      "major": "underground",
      "category": "job",
      "platform": "实习僧",
      "source": "实习僧",
      "title": "室内&#xf718&#xf8f5&#xe651助理",
      "summary": "来自 实习僧 的城市地下空间工程相关实习/就业信息，请以原网站发布时间和要求为准。",
      "url": "https://www.shixiseng.com/intern/inn_av0bas2pmlfj?pcm=pc_SearchList",
      "status": "auto"
    },
    {
      "id": "40a5392530ce5813",
      "major": "underground",
      "category": "job",
      "platform": "实习僧",
      "source": "实习僧",
      "title": "实习活动执&#xf1c1",
      "summary": "来自 实习僧 的城市地下空间工程相关实习/就业信息，请以原网站发布时间和要求为准。",
      "url": "https://www.shixiseng.com/intern/inn_9xwpxmhynbzw?pcm=pc_SearchList",
      "status": "auto"
    },
    {
      "id": "da18e243ec927400",
      "major": "underground",
      "category": "job",
      "platform": "实习僧",
      "source": "实习僧",
      "title": "实习新媒体运营及活动执&#xf1c1",
      "summary": "来自 实习僧 的城市地下空间工程相关实习/就业信息，请以原网站发布时间和要求为准。",
      "url": "https://www.shixiseng.com/intern/inn_whdkdebb1byr?pcm=pc_SearchList",
      "status": "auto"
    },
    {
      "id": "0294fec55a59ccb4",
      "major": "underground",
      "category": "job",
      "platform": "实习僧",
      "source": "实习僧",
      "title": "文案活动策划实习&#xf16c",
      "summary": "来自 实习僧 的城市地下空间工程相关实习/就业信息，请以原网站发布时间和要求为准。",
      "url": "https://www.shixiseng.com/intern/inn_nwklj6clrisx?pcm=pc_SearchList",
      "status": "auto"
    },
    {
      "id": "5a3129042cd0bd00",
      "major": "underground",
      "category": "job",
      "platform": "实习僧",
      "source": "实习僧",
      "title": "城&#xe080分析实习&#xf16c",
      "summary": "来自 实习僧 的城市地下空间工程相关实习/就业信息，请以原网站发布时间和要求为准。",
      "url": "https://www.shixiseng.com/intern/inn_hdqux2ha0hlk?pcm=pc_SearchList",
      "status": "auto"
    },
    {
      "id": "ff88cd349378b61c",
      "major": "underground",
      "category": "job",
      "platform": "实习僧",
      "source": "实习僧",
      "title": "&#xf1cc&#xe744&#xe744城&#xe080&#xe631商实习&#xf16c",
      "summary": "来自 实习僧 的城市地下空间工程相关实习/就业信息，请以原网站发布时间和要求为准。",
      "url": "https://www.shixiseng.com/intern/inn_guopz26fnbwq?pcm=pc_SearchList",
      "status": "auto"
    },
    {
      "id": "95324f7e56c25f18",
      "major": "underground",
      "category": "job",
      "platform": "实习僧",
      "source": "实习僧",
      "title": "城&#xe080战略与公共&#xebda策研究实习&#xf16c",
      "summary": "来自 实习僧 的城市地下空间工程相关实习/就业信息，请以原网站发布时间和要求为准。",
      "url": "https://www.shixiseng.com/intern/inn_fh96ntmliomr?pcm=pc_SearchList",
      "status": "auto"
    },
    {
      "id": "28ef04ab1089926d",
      "major": "underground",
      "category": "job",
      "platform": "智联招聘",
      "source": "智联招聘",
      "title": "智联招聘：城市地下空间工程相关结果页",
      "summary": "已抓取到 智联招聘 的公开搜索页，但页面结构限制了列表解析，请打开原页面查看最新结果。",
      "url": "https://sou.zhaopin.com/?kw=%E5%9F%8E%E5%B8%82%E5%9C%B0%E4%B8%8B%E7%A9%BA%E9%97%B4%E5%B7%A5%E7%A8%8B%20%E5%AE%9E%E4%B9%A0",
      "status": "search-page"
    },
    {
      "id": "1ddde5f0cfb01fd3",
      "major": "underground",
      "category": "job",
      "platform": "前程无忧",
      "source": "前程无忧",
      "title": "前程无忧：城市地下空间工程相关结果页",
      "summary": "已抓取到 前程无忧 的公开搜索页，但页面结构限制了列表解析，请打开原页面查看最新结果。",
      "url": "https://we.51job.com/pc/search?keyword=%E5%9F%8E%E5%B8%82%E5%9C%B0%E4%B8%8B%E7%A9%BA%E9%97%B4%E5%B7%A5%E7%A8%8B%20%E5%AE%9E%E4%B9%A0",
      "status": "search-page"
    },
    {
      "id": "79c6ae41d4d44487",
      "major": "underground",
      "category": "job",
      "platform": "应届生求职网",
      "source": "应届生求职网",
      "title": "应届生求职网：城市地下空间工程 实习",
      "summary": "该来源本次自动抓取受限，已保留公开搜索入口，方便用户进入原平台查看。",
      "url": "https://www.yingjiesheng.com/so.php?word=%E5%9F%8E%E5%B8%82%E5%9C%B0%E4%B8%8B%E7%A9%BA%E9%97%B4%E5%B7%A5%E7%A8%8B%20%E5%AE%9E%E4%B9%A0",
      "status": "fallback"
    },
    {
      "id": "4757ef2bfa60eaee",
      "major": "underground",
      "category": "job",
      "platform": "猎聘",
      "source": "猎聘",
      "title": "混凝土业务员招聘",
      "summary": "来自 猎聘 的城市地下空间工程相关实习/就业信息，请以原网站发布时间和要求为准。",
      "url": "https://www.liepin.com/zphntywy6l6w/",
      "status": "auto"
    },
    {
      "id": "3013084799f166e0",
      "major": "underground",
      "category": "job",
      "platform": "猎聘",
      "source": "猎聘",
      "title": "冰吧企划经理招聘",
      "summary": "来自 猎聘 的城市地下空间工程相关实习/就业信息，请以原网站发布时间和要求为准。",
      "url": "https://www.liepin.com/zpbbqhjl4p4w/",
      "status": "auto"
    }
  ]
}
